LICENSE
MANIFEST.in
README.rst
setup.py
google/__init__.py
google/cloud/__init__.py
google/cloud/proto/__init__.py
google/cloud/proto/logging/__init__.py
google/cloud/proto/logging/v2/__init__.py
google/cloud/proto/logging/v2/log_entry_pb2.py
google/cloud/proto/logging/v2/log_entry_pb2_grpc.py
google/cloud/proto/logging/v2/logging_config_pb2.py
google/cloud/proto/logging/v2/logging_config_pb2_grpc.py
google/cloud/proto/logging/v2/logging_metrics_pb2.py
google/cloud/proto/logging/v2/logging_metrics_pb2_grpc.py
google/cloud/proto/logging/v2/logging_pb2.py
google/cloud/proto/logging/v2/logging_pb2_grpc.py
proto_google_cloud_logging_v2.egg-info/PKG-INFO
proto_google_cloud_logging_v2.egg-info/SOURCES.txt
proto_google_cloud_logging_v2.egg-info/dependency_links.txt
proto_google_cloud_logging_v2.egg-info/namespace_packages.txt
proto_google_cloud_logging_v2.egg-info/requires.txt
proto_google_cloud_logging_v2.egg-info/top_level.txt